rtmplite3/__init__.py
rtmplite3/__main__.py
rtmplite3/amf.py
rtmplite3/common.py
rtmplite3/flv.py
rtmplite3/multitask.py
rtmplite3/rtmp.py
rtmplite3-0.4.0.dist-info/LICENSE
rtmplite3-0.4.0.dist-info/METADATA
rtmplite3-0.4.0.dist-info/WHEEL
rtmplite3-0.4.0.dist-info/entry_points.txt
rtmplite3-0.4.0.dist-info/top_level.txt
rtmplite3-0.4.0.dist-info/RECORD
