Metadata-Version: 2.1
Name: rtmplite3
Version: 0.4.0
Summary: A pure Python 3 RTMP server.
Home-page: https://github.com/KnugiHK/rtmplite3
Author: KnugiHK
Author-email: info@knugi.com
License: UNKNOWN
Platform: UNKNOWN
Classifier: Programming Language :: Python :: 3
Classifier: License :: OSI Approved :: GNU General Public License v3 (GPLv3)
Classifier: Operating System :: OS Independent
Requires-Python: >=3.6
License-File: LICENSE
